setup.py
SL_project/__init__.py
SL_project/ml_model.py
SL_project.egg-info/PKG-INFO
SL_project.egg-info/SOURCES.txt
SL_project.egg-info/dependency_links.txt
SL_project.egg-info/requires.txt
SL_project.egg-info/top_level.txt