Metadata-Version: 2.1
Name: SL-project
Version: 0.0.1
Summary: long description
Home-page: https://gitlab.com/Djeinaba_Doro/test_project
Author: Djeinaba
Author-email: djeinaba.ba@insa.ueuromed.org
License: UNKNOWN
Platform: UNKNOWN
Classifier: Programming Language :: Python :: 3
Classifier: License :: OSI Approved :: MIT License
Classifier: Operating System :: OS Independent
